AUTHORS.rst
CONTRIBUTING.rst
HISTORY.rst
LICENSE
MANIFEST.in
README.rst
setup.cfg
setup.py
clean/__init__.py
clean/auth/__init__.py
clean/auth/abs.py
clean/auth/decorator.py
clean/auth/perm_inspector.py
clean/entities/__init__.py
clean/entities/error.py
clean/entities/resp_status.py
clean/entities/token.py
clean/exceptions/__init__.py
clean/infra/__init__.py
clean/infra/log/__init__.py
clean/infra/log/logger.py
clean/infra/log/utils/__init__.py
clean/infra/log/utils/config.py
clean/infra/log/utils/colors/__init__.py
clean/infra/log/utils/colors/termcolors.py
clean/infra/schema/__init__.py
clean/repository/__init__.py
clean/repository/abs.py
clean/repository/list.py
clean/request/__init__.py
clean/request/filters/__init__.py
clean/request/filters/abs.py
clean/request/filters/loader.py
clean/request/filters/fields/__init__.py
clean/request/filters/fields/datetime_range.py
clean/request/filters/fields/string.py
clean/request/inout/__init__.py
clean/request/inout/actions.py
clean/request/inout/base.py
clean/request/inout/filter.py
clean/request/inout/ports.py
clean/request/serializers/__init__.py
clean/request/serializers/json.py
clean/request/verifier/__init__.py
clean/request/verifier/abs.py
clean/request/verifier/json_schema.py
clean/use_case/__init__.py
clean/use_case/case.py
clean/use_case/common.py
clean/utils/__init__.py
clean/utils/requests.py
clean/utils/unique.py
docs/Makefile
docs/authors.rst
docs/conf.py
docs/contributing.rst
docs/history.rst
docs/index.rst
docs/installation.rst
docs/make.bat
docs/readme.rst
docs/usage.rst
py_clean.egg-info/PKG-INFO
py_clean.egg-info/SOURCES.txt
py_clean.egg-info/dependency_links.txt
py_clean.egg-info/not-zip-safe
py_clean.egg-info/requires.txt
py_clean.egg-info/top_level.txt
tests/__init__.py
tests/clean/__init__.py
tests/clean/auth/__init__.py
tests/clean/auth/test_auth_abs.py
tests/clean/auth/test_auth_imp.py
tests/clean/auth/test_decorator_builder.py
tests/clean/auth/test_perm_inspector.py
tests/clean/entities/__init__.py
tests/clean/entities/test_error_message.py
tests/clean/entities/test_token.py
tests/clean/infra/__init__.py
tests/clean/infra/log/__init__.py
tests/clean/infra/log/utils/__init__.py
