Metadata-Version: 1.1
Name: py-clean
Version: 0.2.0
Summary: python clean architecture toolkit
Home-page: https://github.com/bahnlink/pyclean
Author: bahnlink
Author-email: admin@bahnlink.com
License: UNKNOWN
Keywords: clean architecture toolkit
Platform: UNKNOWN
Classifier: Development Status :: 2 - Pre-Alpha
Classifier: Intended Audience :: Developers
Classifier: Natural Language :: English
Classifier: Programming Language :: Python :: 3.4
Classifier: Programming Language :: Python :: 3.5
Classifier: Programming Language :: Python :: 3.6
